setup.py
yonbip_open_api_sdk/__init__.py
yonbip_open_api_sdk/__version__.py
yonbip_open_api_sdk/cache.py
yonbip_open_api_sdk/request_opt.py
yonbip_open_api_sdk/sign_opt.py
yonbip_open_api_sdk/token_opt.py
yonbip_open_event_sdk/__init__.py
yonbip_open_event_sdk/event_opt.py
yonyouopenapisdk1.egg-info/PKG-INFO
yonyouopenapisdk1.egg-info/SOURCES.txt
yonyouopenapisdk1.egg-info/dependency_links.txt
yonyouopenapisdk1.egg-info/requires.txt
yonyouopenapisdk1.egg-info/top_level.txt