Metadata-Version: 2.1
Name: yonyouopenapisdk1
Version: 0.0.2
Summary: 用友开放平台API访问sdk.
Home-page: https://yonbip.diwork.com
Author: liuyw
Author-email: liuywx@yonyou.com
License: MIT
Platform: UNKNOWN
Classifier: License :: OSI Approved :: MIT License
Classifier: Programming Language :: Python
Classifier: Programming Language :: Python :: 3
Classifier: Programming Language :: Python :: 3.6
Classifier: Programming Language :: Python :: Implementation :: CPython
Classifier: Programming Language :: Python :: Implementation :: PyPy
Requires-Python: >=3.10
